konnect/http/__init__.py
konnect/http/authenticators.py
konnect/http/certificates.py
konnect/http/exceptions.py
konnect/http/py.typed
konnect/http/request.py
konnect/http/response.py
konnect/http/session.py
konnect/http/cookies/__init__.py
konnect/http/cookies/cookie.py
konnect/http/cookies/dates.py
konnect/http/cookies/set_cookie_parser.py
konnect_http-0.3.0.dist-info/WHEEL
konnect_http-0.3.0.dist-info/METADATA
konnect_http-0.3.0.dist-info/RECORD
