Metadata-Version: 2.4
Name: konnect.http
Version: 0.3.0
Summary: Pythonic, asynchronous HTTP client
Author-email: Dom Sekotill <dom.sekotill@kodo.org.uk>
Requires-Python: ~=3.11
Classifier: Development Status :: 3 - Alpha
Classifier: Intended Audience :: Developers
Classifier: License :: OSI Approved :: Mozilla Public License 2.0 (MPL 2.0)
Classifier: Topic :: Internet
Requires-Dist: anyio ~=4.0
Requires-Dist: kodo.quantities
Requires-Dist: konnect.curl ~=0.2.3
